{
  "padding" : "10 10 5 10",
  "border" : false,
  "xtype" : "xcp_form",
  "namespace" : "adcb",
  "categoryID" : "com_emc_xcp_artifact_uistep",
  "artifactName" : "create_case_1_step_",
  "items" : [ {
    "xtype" : "xcp_action_container",
    "actions" : [ ]
  }, {
    "xtype" : "xcp_uievent_publisher",
    "plugins" : [ {
      "ptype" : "xcp_publish_uievents",
      "publish" : [ ]
    } ]
  }, {
    "xcpId" : "create_case_column_box",
    "xtype" : "xcp_column_box",
    "collapsible" : false,
    "collapseFirst" : true,
    "border" : false,
    "defaultMargins" : "5",
    "layout" : "xcp_columnbox",
    "items" : [ {
      "xcpId" : "columnvbox",
      "xtype" : "xcp_columnvbox",
      "orientation" : "Vertical",
      "overflow_x" : "hidden",
      "labelWidth" : 150,
      "labelAlign" : "left",
      "halign" : "left",
      "valign" : "top",
      "defaultMargins" : "5",
      "items" : [ {
        "xcpId" : "case_name",
        "xtype" : "xcp_text_input",
        "fieldLabel" : "${_UI_UIStep_adcb_create_case_1_step__case_name_fieldLabel}",
        "hstretch" : true,
        "valueType" : "STRING",
        "hideErrorInToolTip" : false,
        "stopOnValidationFail" : true,
        "plugins" : [ {
          "ptype" : "xcp_expression_properties",
          "expression" : [ {
            "propertyId" : "mandatory",
            "setterFunName" : "setMandatory",
            "etype" : "case_name_mandatory",
            "events" : [ "application.xcp_action_flow_step_page_load" ],
            "disableInitialEval" : true,
            "disableProcessingOnRender" : false
          } ]
        } ]
      }, {
        "xcpId" : "mobile_number",
        "xtype" : "xcp_text_input",
        "fieldLabel" : "${_UI_UIStep_adcb_create_case_1_step__mobile_number_fieldLabel}",
        "hstretch" : true,
        "valueType" : "STRING",
        "hideErrorInToolTip" : false,
        "stopOnValidationFail" : true,
        "plugins" : [ {
          "ptype" : "xcp_expression_properties",
          "expression" : [ {
            "propertyId" : "mandatory",
            "setterFunName" : "setMandatory",
            "etype" : "mobile_number_mandatory",
            "events" : [ "application.xcp_action_flow_step_page_load" ],
            "disableInitialEval" : true,
            "disableProcessingOnRender" : false
          } ]
        } ]
      }, {
        "xcpId" : "country",
        "xtype" : "xcp_text_input",
        "fieldLabel" : "${_UI_UIStep_adcb_create_case_1_step__country_fieldLabel}",
        "hstretch" : true,
        "valueType" : "STRING",
        "hideErrorInToolTip" : false,
        "stopOnValidationFail" : true,
        "plugins" : [ {
          "ptype" : "xcp_expression_properties",
          "expression" : [ {
            "propertyId" : "mandatory",
            "setterFunName" : "setMandatory",
            "etype" : "country_mandatory",
            "events" : [ "application.xcp_action_flow_step_page_load" ],
            "disableInitialEval" : true,
            "disableProcessingOnRender" : false
          } ]
        } ]
      }, {
        "xcpId" : "state",
        "xtype" : "xcp_text_input",
        "fieldLabel" : "${_UI_UIStep_adcb_create_case_1_step__state_fieldLabel}",
        "hstretch" : true,
        "valueType" : "STRING",
        "hideErrorInToolTip" : false,
        "stopOnValidationFail" : true,
        "plugins" : [ {
          "ptype" : "xcp_expression_properties",
          "expression" : [ {
            "propertyId" : "mandatory",
            "setterFunName" : "setMandatory",
            "etype" : "state_mandatory",
            "events" : [ "application.xcp_action_flow_step_page_load" ],
            "disableInitialEval" : true,
            "disableProcessingOnRender" : false
          } ]
        } ]
      } ]
    }, {
      "xcpId" : "columnvbox1",
      "xtype" : "xcp_columnvbox",
      "orientation" : "Vertical",
      "overflow_x" : "hidden",
      "labelWidth" : 150,
      "labelAlign" : "left",
      "halign" : "left",
      "valign" : "top",
      "defaultMargins" : "5"
    } ]
  } ]
}